{
  "$schema": "https://mintlify.com/schema.json",
  "name": "Docs",
  "logo": {
    "dark": "/logo/dark.svg",
    "light": "/logo/light.svg"
  },
  "favicon": "/favicon.png",
  "colors": {
    "primary": "#7f56d9",
    "light": "#7f56d9",
    "dark": "#7f56d9",
    "anchors": {
      "from": "#7f56d9",
      "to": "#7f56d9"
    }
  },
  "topbarLinks": [
    {
      "name": "Login",
      "url": "https://www.withgale.com/login"
    }
  ],
  "topbarCtaButton": {
    "name": "Get Started ",
    "url": "https://www.withgale.com/signup"
  },
  "tabs": [
  ],
  "navigation": [
    {
      "group": "Get Started",
      "pages": [
        "introduction",
        {
          "group": "Integration",
          "pages": [
            "onboarding/overview",
            "onboarding/woocommerce/installation",
            "onboarding/shopify/installation"
          ]
        }

      ]
    }
   
  ],
  "footerSocials": {
    "linkedin": "https://www.linkedin.com/company/gale-hsa"
  }
}
